chemscii/__init__.py
chemscii/cli.py
chemscii/layout/__init__.py
chemscii/layout/atoms.py
chemscii/layout/bonds.py
chemscii/mcp.py
chemscii/parsers/__init__.py
chemscii/parsers/chembl.py
chemscii/parsers/molecule.py
chemscii/parsers/name.py
chemscii/renderers/__init__.py
chemscii/renderers/ascii.py
chemscii/renderers/base.py
chemscii/renderers/magic.py
chemscii/renderers/unicode.py
chemscii-0.1.2.dist-info/METADATA
chemscii-0.1.2.dist-info/WHEEL
chemscii-0.1.2.dist-info/entry_points.txt
chemscii-0.1.2.dist-info/licenses/LICENSE
chemscii-0.1.2.dist-info/RECORD
