Metadata-Version: 2.4
Name: chemscii
Version: 0.1.2
Summary: Render chemical structures as ASCII/Unicode art
License-File: LICENSE
Author: Benjamin J. Shields
Requires-Python: >=3.10,<4.0
Classifier: Programming Language :: Python :: 3
Classifier: Programming Language :: Python :: 3.10
Classifier: Programming Language :: Python :: 3.11
Classifier: Programming Language :: Python :: 3.12
Classifier: Programming Language :: Python :: 3.13
Classifier: Programming Language :: Python :: 3.14
Requires-Dist: ascii-magic (>=2.7.2,<3.0.0)
Requires-Dist: mcp (>=1.25,<2.0)
Requires-Dist: pillow (>=10.0,<11.0)
Requires-Dist: rdkit (>=2025.0,<2026.0)
Requires-Dist: rich (>=13.0,<14.0)
Requires-Dist: typer (>=0.15,<0.16)
